[{"Person_Position_Name":"董事長","Person_Name":"蔡O忠","Juristic_Person_Name":"","Person_Shareholding":2334000},{"Person_Position_Name":"董事","Person_Name":"梁O承","Juristic_Person_Name":"","Person_Shareholding":10000},{"Person_Position_Name":"董事","Person_Name":"謝O任","Juristic_Person_Name":"","Person_Shareholding":10000},{"Person_Position_Name":"董事","Person_Name":"蔡O紋","Juristic_Person_Name":"","Person_Shareholding":262000},{"Person_Position_Name":"監察人","Person_Name":"蔡O義","Juristic_Person_Name":"","Person_Shareholding":120000}]
