[{"Person_Position_Name":"董事長","Person_Name":"徐O東","Juristic_Person_Name":"","Person_Shareholding":3144},{"Person_Position_Name":"董事","Person_Name":"黃O德","Juristic_Person_Name":"遠東新世紀股份有限公司","Person_Shareholding":186928831},{"Person_Position_Name":"董事","Person_Name":"鄭O宇","Juristic_Person_Name":"遠東新世紀股份有限公司","Person_Shareholding":186928831},{"Person_Position_Name":"董事","Person_Name":"蔡O雄","Juristic_Person_Name":"遠東新世紀股份有限公司","Person_Shareholding":186928831},{"Person_Position_Name":"董事","Person_Name":"徐O芳","Juristic_Person_Name":"遠東百貨股份有限公司","Person_Shareholding":2796},{"Person_Position_Name":"董事","Person_Name":"李O炎","Juristic_Person_Name":"亞洲水泥股份有限公司","Person_Shareholding":178707648},{"Person_Position_Name":"董事","Person_Name":"徐O平","Juristic_Person_Name":"亞洲水泥股份有限公司","Person_Shareholding":178707648},{"Person_Position_Name":"董事","Person_Name":"高O英","Juristic_Person_Name":"亞洲水泥股份有限公司","Person_Shareholding":178707648},{"Person_Position_Name":"董事","Person_Name":"王O誠","Juristic_Person_Name":"裕民貿易股份有限公司","Person_Shareholding":12585},{"Person_Position_Name":"監察人","Person_Name":"王O一","Juristic_Person_Name":"遠鼎投資股份有限公司","Person_Shareholding":64758813},{"Person_Position_Name":"監察人","Person_Name":"張O豐","Juristic_Person_Name":"德勤投資股份有限公司","Person_Shareholding":72989090}]
