[{"Person_Position_Name":"董事長","Person_Name":"劉O偉(Fowai Lau)","Juristic_Person_Name":"荷蘭商 Robert Bosch Investment Nederland B.V.","Person_Shareholding":12418560},{"Person_Position_Name":"董事","Person_Name":"何O恒(Ho Kui Hang)","Juristic_Person_Name":"荷蘭商 Robert Bosch Investment Nederland B.V.","Person_Shareholding":12418560},{"Person_Position_Name":"董事","Person_Name":"JOn Heinz ErhOrd HollmOnn(顏恆文)","Juristic_Person_Name":"荷蘭商 Robert Bosch Investment Nederland B.V.","Person_Shareholding":12418560},{"Person_Position_Name":"監察人","Person_Name":"冼O傑(Sin Sai Kit)","Juristic_Person_Name":"荷蘭商 Robert Bosch Investment Nederland B.V.","Person_Shareholding":12418560}]
