[{"Person_Position_Name":"董事長","Person_Name":"賴O徹","Juristic_Person_Name":"聯華氣體工業股份有限公司","Person_Shareholding":10105946},{"Person_Position_Name":"董事","Person_Name":"劉O良","Juristic_Person_Name":"國軍退除役官兵輔導委員會","Person_Shareholding":13345023},{"Person_Position_Name":"董事","Person_Name":"張O","Juristic_Person_Name":"聯華氣體工業股份有限公司","Person_Shareholding":10105946},{"Person_Position_Name":"董事","Person_Name":"湯O孟","Juristic_Person_Name":"聯華氣體工業股份有限公司","Person_Shareholding":10105946},{"Person_Position_Name":"董事","Person_Name":"李O定","Juristic_Person_Name":"聯華氣體工業股份有限公司","Person_Shareholding":10105946},{"Person_Position_Name":"董事","Person_Name":"林O壹","Juristic_Person_Name":"國軍退除役官兵輔導委員會","Person_Shareholding":13345023},{"Person_Position_Name":"董事","Person_Name":"張O林","Juristic_Person_Name":"國軍退除役官兵輔導委員會","Person_Shareholding":13345023},{"Person_Position_Name":"監察人","Person_Name":"王O強","Juristic_Person_Name":"遠東氣體工業股份有限公司","Person_Shareholding":10033340},{"Person_Position_Name":"監察人","Person_Name":"(O察人暫缺1位)","Juristic_Person_Name":"","Person_Shareholding":0}]
