[{"Person_Position_Name":"董事長","Person_Name":"許O寬","Juristic_Person_Name":"英屬維京群島商世界聯合資產投資有限公司","Person_Shareholding":4467480},{"Person_Position_Name":"副董事長","Person_Name":"蘇O邦","Juristic_Person_Name":"和泰汽車股份有限公司","Person_Shareholding":25438987},{"Person_Position_Name":"董事","Person_Name":"周O賢","Juristic_Person_Name":"通中投資股份有限公司","Person_Shareholding":7264259},{"Person_Position_Name":"董事","Person_Name":"黃O光","Juristic_Person_Name":"和泰汽車股份有限公司","Person_Shareholding":25438987},{"Person_Position_Name":"董事","Person_Name":"周O錫","Juristic_Person_Name":"通中投資股份有限公司","Person_Shareholding":7264259},{"Person_Position_Name":"董事","Person_Name":"龔O芬","Juristic_Person_Name":"通中投資股份有限公司","Person_Shareholding":7264259},{"Person_Position_Name":"董事","Person_Name":"周O月惠","Juristic_Person_Name":"","Person_Shareholding":1302712},{"Person_Position_Name":"監察人","Person_Name":"劉O森","Juristic_Person_Name":"和展投資有限公司","Person_Shareholding":2000},{"Person_Position_Name":"監察人","Person_Name":"郭O伶","Juristic_Person_Name":"通日實業股份有限公司","Person_Shareholding":730171}]
