[{"Person_Position_Name":"董事長","Person_Name":"龔O權(Kuo-Chuan Kung)","Juristic_Person_Name":"馬來西亞商  Nexus Point (Malaysia) SDH. BHD","Person_Shareholding":22164104},{"Person_Position_Name":"董事","Person_Name":"李O(Min Li)","Juristic_Person_Name":"馬來西亞商  Nexus Point (Malaysia) SDH. BHD","Person_Shareholding":22164104},{"Person_Position_Name":"董事","Person_Name":"黃O忠(Tony Huang)","Juristic_Person_Name":"馬來西亞商  Nexus Point (Malaysia) SDH. BHD","Person_Shareholding":22164104},{"Person_Position_Name":"董事","Person_Name":"BOuno, OobeOt MeOcieO","Juristic_Person_Name":"馬來西亞商  Nexus Point (Malaysia) SDH. BHD","Person_Shareholding":22164104},{"Person_Position_Name":"監察人","Person_Name":"姚O文(Fai-Man Yiu)","Juristic_Person_Name":"馬來西亞商  Nexus Point (Malaysia) SDH. BHD","Person_Shareholding":22164104}]
