[{"Person_Position_Name":"董事長","Person_Name":"大O信介","Juristic_Person_Name":"日商株式會社 VIEW TRAVEL SERVICE","Person_Shareholding":30670},{"Person_Position_Name":"副董事長","Person_Name":"大O戶修二","Juristic_Person_Name":"日商株式會社 VIEW TRAVEL SERVICE","Person_Shareholding":30670},{"Person_Position_Name":"董事","Person_Name":"森O鉄郎","Juristic_Person_Name":"日商株式會社 VIEW TRAVEL SERVICE","Person_Shareholding":30670},{"Person_Position_Name":"董事","Person_Name":"堀O和王","Juristic_Person_Name":"日商株式會社 VIEW TRAVEL SERVICE","Person_Shareholding":30670},{"Person_Position_Name":"董事","Person_Name":"高O徹","Juristic_Person_Name":"日商 JALPAK Co., Ltd.","Person_Shareholding":15330},{"Person_Position_Name":"董事","Person_Name":"梶O啓之","Juristic_Person_Name":"日商 JALPAK Co., Ltd.","Person_Shareholding":15330},{"Person_Position_Name":"監察人","Person_Name":"三O俊造","Juristic_Person_Name":"","Person_Shareholding":0},{"Person_Position_Name":"監察人","Person_Name":"吳O齡","Juristic_Person_Name":"","Person_Shareholding":0}]
