[{"Person_Position_Name":"董事長","Person_Name":"林O田","Juristic_Person_Name":"","Person_Shareholding":2435707},{"Person_Position_Name":"董事","Person_Name":"吳O蘭","Juristic_Person_Name":"萬事興股份有限公司","Person_Shareholding":11940565},{"Person_Position_Name":"董事","Person_Name":"張O堆","Juristic_Person_Name":"三金投資股份有限公司","Person_Shareholding":517283},{"Person_Position_Name":"董事","Person_Name":"陳O成","Juristic_Person_Name":"","Person_Shareholding":1264818},{"Person_Position_Name":"董事","Person_Name":"李O淑","Juristic_Person_Name":"","Person_Shareholding":180753},{"Person_Position_Name":"獨立董事","Person_Name":"蔡O","Juristic_Person_Name":"","Person_Shareholding":0},{"Person_Position_Name":"獨立董事","Person_Name":"曹O旺","Juristic_Person_Name":"","Person_Shareholding":0},{"Person_Position_Name":"監察人","Person_Name":"林O明","Juristic_Person_Name":"","Person_Shareholding":859732},{"Person_Position_Name":"監察人","Person_Name":"林O性","Juristic_Person_Name":"","Person_Shareholding":77418},{"Person_Position_Name":"監察人","Person_Name":"郭O祿","Juristic_Person_Name":"","Person_Shareholding":0}]
