[{"Person_Position_Name":"董事長","Person_Name":"魏O谷","Juristic_Person_Name":"經濟部","Person_Shareholding":125890370},{"Person_Position_Name":"董事","Person_Name":"胡O澤","Juristic_Person_Name":"經濟部","Person_Shareholding":125890370},{"Person_Position_Name":"董事","Person_Name":"董O琪","Juristic_Person_Name":"經濟部","Person_Shareholding":125890370},{"Person_Position_Name":"董事","Person_Name":"黃O隆","Juristic_Person_Name":"經濟部","Person_Shareholding":125890370},{"Person_Position_Name":"董事","Person_Name":"吳O明","Juristic_Person_Name":"經濟部","Person_Shareholding":125890370},{"Person_Position_Name":"董事","Person_Name":"王O峰","Juristic_Person_Name":"經濟部","Person_Shareholding":125890370},{"Person_Position_Name":"董事","Person_Name":"邱O金","Juristic_Person_Name":"經濟部","Person_Shareholding":125890370},{"Person_Position_Name":"董事","Person_Name":"梁O傑","Juristic_Person_Name":"經濟部","Person_Shareholding":125890370},{"Person_Position_Name":"董事","Person_Name":"胡O蒂","Juristic_Person_Name":"經濟部","Person_Shareholding":125890370},{"Person_Position_Name":"董事","Person_Name":"陳O賢","Juristic_Person_Name":"經濟部","Person_Shareholding":125890370},{"Person_Position_Name":"董事","Person_Name":"方O呈","Juristic_Person_Name":"經濟部","Person_Shareholding":125890370},{"Person_Position_Name":"董事","Person_Name":"陳O益","Juristic_Person_Name":"經濟部","Person_Shareholding":125890370},{"Person_Position_Name":"董事","Person_Name":"吳O雪","Juristic_Person_Name":"經濟部","Person_Shareholding":125890370},{"Person_Position_Name":"董事","Person_Name":"缺O","Juristic_Person_Name":"","Person_Shareholding":0},{"Person_Position_Name":"董事","Person_Name":"蘇O凱","Juristic_Person_Name":"","Person_Shareholding":0},{"Person_Position_Name":"監察人","Person_Name":"林O發","Juristic_Person_Name":"基隆市政府","Person_Shareholding":1821356},{"Person_Position_Name":"監察人","Person_Name":"邱O斌","Juristic_Person_Name":"新北市政府","Person_Shareholding":978968},{"Person_Position_Name":"監察人","Person_Name":"游O華","Juristic_Person_Name":"桃園市政府","Person_Shareholding":84478},{"Person_Position_Name":"監察人","Person_Name":"高O翔","Juristic_Person_Name":"臺中市政府","Person_Shareholding":3242957},{"Person_Position_Name":"監察人","Person_Name":"許O鈴","Juristic_Person_Name":"南投縣政府","Person_Shareholding":38128}]
