[{"Person_Position_Name":"董事長","Person_Name":"王O博","Juristic_Person_Name":"","Person_Shareholding":21594350},{"Person_Position_Name":"董事","Person_Name":"王O棻","Juristic_Person_Name":"","Person_Shareholding":0},{"Person_Position_Name":"董事","Person_Name":"陳O榮","Juristic_Person_Name":"","Person_Shareholding":0},{"Person_Position_Name":"董事","Person_Name":"施O豪","Juristic_Person_Name":"","Person_Shareholding":11110},{"Person_Position_Name":"董事","Person_Name":"吳O耘","Juristic_Person_Name":"","Person_Shareholding":0},{"Person_Position_Name":"獨立董事","Person_Name":"李O憲","Juristic_Person_Name":"","Person_Shareholding":0},{"Person_Position_Name":"獨立董事","Person_Name":"林O竹","Juristic_Person_Name":"","Person_Shareholding":0},{"Person_Position_Name":"監察人","Person_Name":"簡O成","Juristic_Person_Name":"","Person_Shareholding":0},{"Person_Position_Name":"監察人","Person_Name":"張O源","Juristic_Person_Name":"","Person_Shareholding":0}]
