[{"Person_Position_Name":"董事長","Person_Name":"曾O平","Juristic_Person_Name":"","Person_Shareholding":225000},{"Person_Position_Name":"董事","Person_Name":"吳O中","Juristic_Person_Name":"","Person_Shareholding":225000},{"Person_Position_Name":"董事","Person_Name":"林O志","Juristic_Person_Name":"","Person_Shareholding":0},{"Person_Position_Name":"董事","Person_Name":"黃O智","Juristic_Person_Name":"","Person_Shareholding":0},{"Person_Position_Name":"監察人","Person_Name":"林O棠","Juristic_Person_Name":"","Person_Shareholding":0}]
