[{"Person_Position_Name":"董事","Person_Name":"周O杰","Juristic_Person_Name":"","Person_Shareholding":187500},{"Person_Position_Name":"董事","Person_Name":"洪O德","Juristic_Person_Name":"","Person_Shareholding":187500},{"Person_Position_Name":"董事","Person_Name":"劉O萍","Juristic_Person_Name":"","Person_Shareholding":0},{"Person_Position_Name":"監察人","Person_Name":"許O芬","Juristic_Person_Name":"","Person_Shareholding":187500},{"Person_Position_Name":"董事長","Person_Name":"楊O志","Juristic_Person_Name":"","Person_Shareholding":7500}]
