[{"Person_Position_Name":"董事","Person_Name":"洪O興","Juristic_Person_Name":"台北富邦商業銀行股份有限公司","Person_Shareholding":10000000},{"Person_Position_Name":"董事","Person_Name":"李O鳴","Juristic_Person_Name":"臺灣土地銀行股份有限公司","Person_Shareholding":5000000},{"Person_Position_Name":"董事長","Person_Name":"吳O世","Juristic_Person_Name":"兆豐國際商業銀行股份有限公司","Person_Shareholding":10000000},{"Person_Position_Name":"董事","Person_Name":"曾O杰","Juristic_Person_Name":"台北富邦商業銀行股份有限公司","Person_Shareholding":10000000},{"Person_Position_Name":"董事","Person_Name":"李O忠","Juristic_Person_Name":"合作金庫商業銀行股份有限公司","Person_Shareholding":10000000},{"Person_Position_Name":"董事","Person_Name":"楊O巖","Juristic_Person_Name":"華南商業銀行股份有限公司","Person_Shareholding":5000000},{"Person_Position_Name":"董事","Person_Name":"吳O葉","Juristic_Person_Name":"臺灣中小企業銀行股份有限公司","Person_Shareholding":5000000},{"Person_Position_Name":"董事","Person_Name":"徐O鳳","Juristic_Person_Name":"第一商業銀行股份有限公司","Person_Shareholding":5000000},{"Person_Position_Name":"董事","Person_Name":"蕭O美","Juristic_Person_Name":"兆豐國際商業銀行股份有限公司","Person_Shareholding":10000000},{"Person_Position_Name":"監察人","Person_Name":"林O良","Juristic_Person_Name":"臺灣銀行股份有限公司","Person_Shareholding":10000000},{"Person_Position_Name":"監察人","Person_Name":"李O","Juristic_Person_Name":"臺灣銀行股份有限公司","Person_Shareholding":10000000},{"Person_Position_Name":"監察人","Person_Name":"林O鳳","Juristic_Person_Name":"彰化商業銀行股份有限公司","Person_Shareholding":5000000}]
