[{"Person_Position_Name":"董事","Person_Name":"尚O資產管理股份有限公司","Juristic_Person_Name":"","Person_Shareholding":3491697},{"Person_Position_Name":"監察人","Person_Name":"蔡O玲","Juristic_Person_Name":"","Person_Shareholding":248647},{"Person_Position_Name":"董事","Person_Name":"張O峰","Juristic_Person_Name":"","Person_Shareholding":333405},{"Person_Position_Name":"董事長","Person_Name":"張O稜","Juristic_Person_Name":"","Person_Shareholding":757693},{"Person_Position_Name":"監察人","Person_Name":"許O發","Juristic_Person_Name":"","Person_Shareholding":51000},{"Person_Position_Name":"董事","Person_Name":"得O投資有限公司","Juristic_Person_Name":"","Person_Shareholding":54425},{"Person_Position_Name":"董事","Person_Name":"張O錚","Juristic_Person_Name":"","Person_Shareholding":771616}]
