[{"Person_Position_Name":"董事長","Person_Name":"梁O宗","Juristic_Person_Name":"","Person_Shareholding":3811358},{"Person_Position_Name":"董事","Person_Name":"李O經","Juristic_Person_Name":"","Person_Shareholding":288800},{"Person_Position_Name":"董事","Person_Name":"陳O鴻","Juristic_Person_Name":"","Person_Shareholding":604129},{"Person_Position_Name":"董事","Person_Name":"陳O州","Juristic_Person_Name":"","Person_Shareholding":1121247},{"Person_Position_Name":"董事","Person_Name":"劉O民","Juristic_Person_Name":"","Person_Shareholding":458800},{"Person_Position_Name":"董事","Person_Name":"曾O舜","Juristic_Person_Name":"","Person_Shareholding":1031633},{"Person_Position_Name":"董事","Person_Name":"余O長","Juristic_Person_Name":"","Person_Shareholding":1222974},{"Person_Position_Name":"董事","Person_Name":"周O益","Juristic_Person_Name":"","Person_Shareholding":472},{"Person_Position_Name":"獨立董事","Person_Name":"蔡O良","Juristic_Person_Name":"","Person_Shareholding":649},{"Person_Position_Name":"獨立董事","Person_Name":"詹O芬","Juristic_Person_Name":"","Person_Shareholding":0},{"Person_Position_Name":"獨立董事","Person_Name":"呂O文","Juristic_Person_Name":"","Person_Shareholding":0}]
